jupyterlab_more_shortcuts/__init__.py
jupyterlab_more_shortcuts/_version.py
jupyterlab_more_shortcuts-0.1.0.data/data/share/jupyter/labextensions/jupyterlab_more_shortcuts/build_log.json
jupyterlab_more_shortcuts-0.1.0.data/data/share/jupyter/labextensions/jupyterlab_more_shortcuts/package.json
jupyterlab_more_shortcuts-0.1.0.data/data/share/jupyter/labextensions/jupyterlab_more_shortcuts/static/lib_index_js-webpack_sharing_consume_default_codemirror_language-webpack_sharing_consume_defa-b936d0.66d6006fc751f5f66c71.js
jupyterlab_more_shortcuts-0.1.0.data/data/share/jupyter/labextensions/jupyterlab_more_shortcuts/static/lib_index_js-webpack_sharing_consume_default_codemirror_language-webpack_sharing_consume_defa-b936d0.66d6006fc751f5f66c71.js.map
jupyterlab_more_shortcuts-0.1.0.data/data/share/jupyter/labextensions/jupyterlab_more_shortcuts/static/remoteEntry.51e8b9f64f1fbc793596.js
jupyterlab_more_shortcuts-0.1.0.data/data/share/jupyter/labextensions/jupyterlab_more_shortcuts/static/remoteEntry.51e8b9f64f1fbc793596.js.map
jupyterlab_more_shortcuts-0.1.0.data/data/share/jupyter/labextensions/jupyterlab_more_shortcuts/static/style.js
jupyterlab_more_shortcuts-0.1.0.data/data/share/jupyter/labextensions/jupyterlab_more_shortcuts/static/style_index_js.eb74eb0721ed4edf100b.js
jupyterlab_more_shortcuts-0.1.0.data/data/share/jupyter/labextensions/jupyterlab_more_shortcuts/static/style_index_js.eb74eb0721ed4edf100b.js.map
jupyterlab_more_shortcuts-0.1.0.data/data/share/jupyter/labextensions/jupyterlab_more_shortcuts/static/vendors-node_modules_codemirror_commands_dist_index_js-node_modules_codemirror_search_dist_index_js.3a9b5a5ac4b8336586bc.js
jupyterlab_more_shortcuts-0.1.0.data/data/share/jupyter/labextensions/jupyterlab_more_shortcuts/static/vendors-node_modules_codemirror_commands_dist_index_js-node_modules_codemirror_search_dist_index_js.3a9b5a5ac4b8336586bc.js.map
jupyterlab_more_shortcuts-0.1.0.dist-info/METADATA
jupyterlab_more_shortcuts-0.1.0.dist-info/WHEEL
jupyterlab_more_shortcuts-0.1.0.dist-info/licenses/LICENSE
jupyterlab_more_shortcuts-0.1.0.dist-info/RECORD
