Metadata-Version: 2.3
Name: jupyterlab_more_shortcuts
Version: 0.1.0
Dynamic: Keywords
Summary: Bring more editor shortcuts to jupyterlab settings.
Project-URL: Homepage, https://github.com/zhangfeiran/jupyterlab_more_shortcuts
Project-URL: Bug Tracker, https://github.com/zhangfeiran/jupyterlab_more_shortcuts/issues
Project-URL: Repository, https://github.com/zhangfeiran/jupyterlab_more_shortcuts.git
Author: Frz
License: MIT License
License-File: LICENSE
Classifier: Framework :: Jupyter
Classifier: Framework :: Jupyter :: JupyterLab
Classifier: Framework :: Jupyter :: JupyterLab :: 4
Classifier: Framework :: Jupyter :: JupyterLab :: Extensions
Classifier: Framework :: Jupyter :: JupyterLab :: Extensions :: Prebuilt
Classifier: License :: OSI Approved :: BSD License
Classifier: Programming Language :: Python
Classifier: Programming Language :: Python :: 3
Classifier: Programming Language :: Python :: 3.8
Classifier: Programming Language :: Python :: 3.9
Classifier: Programming Language :: Python :: 3.10
Classifier: Programming Language :: Python :: 3.11
Classifier: Programming Language :: Python :: 3.12
Requires-Python: >=3.8
